tuidbtv/__init__.py
tuidbtv/__main__.py
tuidbtv/config/__init__.py
tuidbtv/config/ConfigParser.py
tuidbtv/controllers/__init__.py
tuidbtv/controllers/ControllerFactory.py
tuidbtv/controllers/DBController.py
tuidbtv/controllers/MySQLController.py
tuidbtv/controllers/PostgresController.py
tuidbtv/controllers/SQLLiteController.py
tuidbtv/default.css
tuidbtv/enums_and_variables/__init__.py
tuidbtv/signals/__init__.py
tuidbtv/suggesters/__init__.py
tuidbtv/suggesters/SuggesterDict.py
tuidbtv/widgets/__init__.py
tuidbtv/widgets/forms/__init__.py
tuidbtv/widgets/forms/ConnectionForms.py
tuidbtv/widgets/NewConnection.py
tuidbtv/widgets/PopUpScreen.py
tuidbtv/widgets/PreviewData.py
tuidbtv/widgets/QuitScreen.py
tuidbtv/widgets/SelectConnection.py
tuidbtv/widgets/SQLEditor.py
tuidbtv-0.2.0.dist-info/entry_points.txt
tuidbtv-0.2.0.dist-info/LICENSE
tuidbtv-0.2.0.dist-info/METADATA
tuidbtv-0.2.0.dist-info/WHEEL
tuidbtv-0.2.0.dist-info/RECORD
